SurvivalScale/Bootstrap.py
SurvivalScale/Marginal.py
SurvivalScale/Solver.py
SurvivalScale/__init__.py
SurvivalScale/getResults.py
survivalscale-0.0.9.dist-info/METADATA
survivalscale-0.0.9.dist-info/WHEEL
survivalscale-0.0.9.dist-info/licenses/LICENSE
survivalscale-0.0.9.dist-info/RECORD
