Metadata-Version: 2.4
Name: SurvivalScale
Version: 0.0.9
Summary: Package to compute survival scale estimates.
Project-URL: Homepage, https://github.com/tazzben/Likert-estimation
Project-URL: Bug Tracker, https://github.com/tazzben/Likert-estimation/issues
Author-email: Ben Smith <bosmith@unomaha.edu>
Maintainer-email: Ben Smith <bosmith@unomaha.edu>
License-Expression: MIT
License-File: LICENSE
Keywords: Bootstrap,Statistics,Survey
Classifier: Intended Audience :: Science/Research
Classifier: License :: OSI Approved :: MIT License
Classifier: Programming Language :: Python :: 3.9
Classifier: Programming Language :: Python :: 3.10
Classifier: Programming Language :: Python :: 3.11
Classifier: Programming Language :: Python :: 3.12
Classifier: Programming Language :: Python :: 3.13
Requires-Python: >=3.9
Requires-Dist: numba>=0.54.0
Requires-Dist: numpy>=1.21.0
Requires-Dist: pandas>=1.3.0
Requires-Dist: scipy>=1.4.0
Requires-Dist: tqdm>=4.26.0
